README.md
setup.cfg
setup.py
messy/__init__.py
messy/config.py
messy.egg-info/PKG-INFO
messy.egg-info/SOURCES.txt
messy.egg-info/dependency_links.txt
messy.egg-info/top_level.txt
tests/fixtures/__init__.py
tests/strategies/__init__.py