Metadata-Version: 1.1
Name: messy
Version: 0.0.0
Summary: Python project template.
Home-page: https://github.com/not4drugs/messy/
Author: John Doe
Author-email: not4drugs@protonmail.com
License: UNKNOWN
Download-URL: https://github.com/not4drugs/messy/archive/master.zip
Platform: UNKNOWN
